rag_plusplus-0.1.0.dist-info/METADATA
rag_plusplus-0.1.0.dist-info/WHEEL
rag_plusplus/__init__.py
rag_plusplus/_rag_plusplus_rs.abi3.so
rag_plusplus/py.typed
rag_plusplus-0.1.0.dist-info/RECORD
