Metadata-Version: 2.4
Name: rag-plusplus
Version: 0.1.0
Classifier: Development Status :: 4 - Beta
Classifier: Intended Audience :: Developers
Classifier: Intended Audience :: Science/Research
Classifier: License :: OSI Approved :: MIT License
Classifier: Operating System :: OS Independent
Classifier: Programming Language :: Python :: 3
Classifier: Programming Language :: Python :: 3.9
Classifier: Programming Language :: Python :: 3.10
Classifier: Programming Language :: Python :: 3.11
Classifier: Programming Language :: Python :: 3.12
Classifier: Programming Language :: Rust
Classifier: Topic :: Scientific/Engineering :: Artificial Intelligence
Requires-Dist: numpy>=1.21.0
Requires-Dist: pytest>=7.0.0 ; extra == 'dev'
Requires-Dist: pytest-benchmark>=4.0.0 ; extra == 'dev'
Requires-Dist: mypy>=1.5.0 ; extra == 'dev'
Requires-Dist: ruff>=0.1.0 ; extra == 'dev'
Provides-Extra: dev
Summary: RAG++: High-performance retrieval for memory-conditioned selection (Rust core with Python bindings)
Keywords: retrieval,rag,vector-search,hnsw,trajectory,rust,pyo3
Author: Mohamed Diomande
License: MIT
Requires-Python: >=3.9
Project-URL: Homepage, https://github.com/mohameddiomande/rag-plusplus
Project-URL: Repository, https://github.com/mohameddiomande/rag-plusplus
Project-URL: Documentation, https://github.com/mohameddiomande/rag-plusplus#readme
